{
	"archive" : {},
	"artifacts" : 
	[
		{
			"path" : "libs/generating/libgenerating.a"
		}
	],
	"backtrace" : 1,
	"backtraceGraph" : 
	{
		"commands" : 
		[
			"add_library"
		],
		"files" : 
		[
			"libs/generating/CMakeLists.txt"
		],
		"nodes" : 
		[
			{
				"file" : 0
			},
			{
				"command" : 0,
				"file" : 0,
				"line" : 1,
				"parent" : 0
			}
		]
	},
	"compileGroups" : 
	[
		{
			"compileCommandFragments" : 
			[
				{
					"fragment" : "-g"
				},
				{
					"fragment" : "-std=gnu11"
				}
			],
			"language" : "C",
			"languageStandard" : 
			{
				"backtraces" : 
				[
					1
				],
				"standard" : "11"
			},
			"sourceIndexes" : 
			[
				1
			]
		}
	],
	"id" : "generating::@44262a4f1dc5ded9642e",
	"name" : "generating",
	"nameOnDisk" : "libgenerating.a",
	"paths" : 
	{
		"build" : "libs/generating",
		"source" : "libs/generating"
	},
	"sourceGroups" : 
	[
		{
			"name" : "Header Files",
			"sourceIndexes" : 
			[
				0
			]
		},
		{
			"name" : "Source Files",
			"sourceIndexes" : 
			[
				1
			]
		}
	],
	"sources" : 
	[
		{
			"backtrace" : 1,
			"path" : "libs/generating/generatingFunc.h",
			"sourceGroupIndex" : 0
		},
		{
			"backtrace" : 1,
			"compileGroupIndex" : 0,
			"path" : "libs/generating/generatingFunc.c",
			"sourceGroupIndex" : 1
		}
	],
	"type" : "STATIC_LIBRARY"
}
